[{
    "id": 1,
    "name": "Oscar Cortez",
    "title": "Developer",
    "company": "Kronoscode, MotMot Studio",
    "country": "Nicaragua",
    "photoUrl": "../../images/people/oscar_cortez.jpg",
    "bio": "I'm a 20 years old System Engineer student from Nicaragua. I'm a passionated and evangelist of the free software and open sources tools. Lover of Javascript and Python. I want solve problems with a text editor and compiler, I enjoy to create powerful apps for the web, mobile and desktop based in a potent backend, with a sutil front end living in a robust cloud.",
    "tags": ["Polymer", "Python"],
    "badges": [{
        "name": "GDG",
        "description": "Google Developers Group Managua",
        "link": "https://developers.google.com/groups/chapter/100514812580249787371/"
    }],
    "socials": [{
        "name": "Website",
        "link": "http://www.oscarmcm.com/"
    }, {
        "name": "Twitter",
        "link": "https://twitter.com/oscar_mcm"
    }, {
        "name": "GitHub",
        "link": "https://github.com/oscar_mcm"
    }]
}]
